snapshell/__init__.py
snapshell/cli.py
snapshell/llm_api.py
snapshell/utils.py
snapshell/package_managers/__init__.py
snapshell/package_managers/apt_package_manager.py
snapshell/package_managers/base_package_manager.py
snapshell/package_managers/dpkg_package_manager.py
snapshell/package_managers/pacman_package_manager.py
snapshell/package_managers/pamac_package_manager.py
snapshell-1.1.2.dist-info/LICENSE
snapshell-1.1.2.dist-info/METADATA
snapshell-1.1.2.dist-info/WHEEL
snapshell-1.1.2.dist-info/entry_points.txt
snapshell-1.1.2.dist-info/top_level.txt
snapshell-1.1.2.dist-info/RECORD
