Metadata-Version: 2.1
Name: snapshell
Version: 1.1.2
Summary: An AI-powered tool to suggest Linux commands based on user input
Home-page: https://github.com/KTS-o7/snapshell
Author: Krishnatejaswi S
Author-email: shentharkrishnatejaswi@gmail.com
Classifier: Programming Language :: Python :: 3
Classifier: License :: OSI Approved :: MIT License
Classifier: Operating System :: OS Independent
Requires-Python: >=3.10
License-File: LICENSE
Requires-Dist: groq
Requires-Dist: requests
Requires-Dist: instructor
Requires-Dist: pydantic
Requires-Dist: tqdm
